README
opts.py
setup.cfg
setup.py
opts.egg-info/PKG-INFO
opts.egg-info/SOURCES.txt
opts.egg-info/dependency_links.txt
opts.egg-info/not-zip-safe
opts.egg-info/top_level.txt