Metadata-Version: 1.0
Name: opts
Version: 0.1
Summary: commandline option parser
Home-page: http://github.com/DasIch/opts
Author: Daniel Neuhäuser
Author-email: dasdasich@gmail.com
License: BSD
Keywords: commandline option parser
Platform: any
